vscode_cli_helpers/__init__.py
vscode_cli_helpers/open_file/__init__.py
vscode_cli_helpers/open_file/config_reader.py
vscode_cli_helpers/open_file/data/__init__.py
vscode_cli_helpers/open_file/data/templates/__init__.py
vscode_cli_helpers/open_file/data/templates/python.txt
vscode_cli_helpers/open_file/exceptions.py
vscode_cli_helpers/open_file/script.py
vscode_cli_helpers-0.1.0.dist-info/METADATA
vscode_cli_helpers-0.1.0.dist-info/WHEEL
vscode_cli_helpers-0.1.0.dist-info/entry_points.txt
vscode_cli_helpers-0.1.0.dist-info/RECORD
